{
"coc.preferences.formatOnSaveFiletypes": [
"json",
"css",
"markdown"
],
"eslint.autoFixOnSave": true,
"eslint.autoFix": true,
"tsserver.enableJavascript": false,
"languageserver": {
"flow": {
"command": "flow",
"args": [
"lsp"
],
"filetypes": [
"javascript",
"javascriptreact"
],
"initializationOptions": {},
"requireRootPattern": true,
"settings": {},
"rootPatterns": [
".flowconfig"
]
}
},
"diagnostic.errorSign": "✘",
"diagnostic.warningSign": "",
"diagnostic.infoSign": "",
"suggest.completionItemKindLabels": {
"keyword": "",
"variable": "",
"value": "",
"operator": "Ψ",
"function": "ƒ",
"reference": "渚",
"constant": "",
"method": "",
"struct": "פּ",
"class": "",
"interface": "",
"text": "",
"enum": "",
"enumMember": "",
"module": "",
"color": "",
"property": "",
"field": "",
"unit": "",
"event": "鬒",
"file": "",
"folder": "",
"snippet": "",
"typeParameter": "",
"default": ""
}
}
